.editorconfig
.gitignore
AUTHORS.rst
CONTRIBUTING.rst
LICENSE
MANIFEST.in
Makefile
README.rst
readthedocs.yaml
requirements.txt
requirements_dev.txt
setup.cfg
setup.py
.github/ISSUE_TEMPLATE.md
.github/workflows/new_pypi_release.yml
.github/workflows/unittest.yml
docs/.gitignore
docs/Makefile
docs/authors.rst
docs/changelogs.rst
docs/cli.rst
docs/conf.py
docs/contributing.rst
docs/history.rst
docs/index.rst
docs/installation.rst
docs/make.bat
docs/master_config.rst
docs/readme.rst
docs/usage.rst
examples/gui_config.ini
examples/master.ini
examples/any/config.ini
examples/any/config_full.ini
examples/any/master.ini
examples/simple/config.ini
examples/simple/master.ini
inicheck/__init__.py
inicheck/changes.py
inicheck/checkers.py
inicheck/cli.py
inicheck/config.py
inicheck/entries.py
inicheck/iniparse.py
inicheck/output.py
inicheck/tools.py
inicheck/utilities.py
m3w_inicheck.egg-info/PKG-INFO
m3w_inicheck.egg-info/SOURCES.txt
m3w_inicheck.egg-info/dependency_links.txt
m3w_inicheck.egg-info/entry_points.txt
m3w_inicheck.egg-info/not-zip-safe
m3w_inicheck.egg-info/requires.txt
m3w_inicheck.egg-info/top_level.txt
tests/__init__.py
tests/conftest.py
tests/test_changes.py
tests/test_checkers.py
tests/test_cli.py
tests/test_config.py
tests/test_entries.py
tests/test_output.py
tests/test_parsing.py
tests/test_tools.py
tests/test_utilities.py
tests/test_configs/CoreConfig.ini
tests/test_configs/base_cfg.ini
tests/test_configs/change_log.ini
tests/test_configs/changelog.ini
tests/test_configs/changelog_test_old.ini
tests/test_configs/full_config.ini
tests/test_configs/master.ini
tests/test_configs/old_smrf_config.ini
tests/test_configs/recipes.ini