Metadata-Version: 2.1
Name: m3w-inicheck
Version: 0.2.2
Summary: inicheck is an high level configuration file checker enabling developers tight control over their users configuration files
Home-page: https://github.com/USDA-ARS-NWRC/inicheck
Author: USDA ARS NWRC
Author-email: snow@ars.usda.gov
License: CC0 1.0 Universal (CC0 1.0) Public Domain Dedication
Project-URL: Documentation, https://inicheck.readthedocs.io
Keywords: inicheck
Platform: UNKNOWN
Classifier: Development Status :: 4 - Beta
Classifier: Intended Audience :: Developers
Classifier: License :: CC0 1.0 Universal (CC0 1.0) Public Domain Dedication
Classifier: Natural Language :: English
Classifier: Programming Language :: Python :: 3.7
Classifier: Programming Language :: Python :: 3.8
Classifier: Programming Language :: Python :: 3.9
Classifier: Programming Language :: Python :: 3.10
Classifier: Programming Language :: Python :: 3.11
License-File: LICENSE
License-File: AUTHORS.rst
